banglanltk/__init__.py
banglanltk-0.0.4.dist-info/LICENSE.txt
banglanltk-0.0.4.dist-info/METADATA
banglanltk-0.0.4.dist-info/WHEEL
banglanltk-0.0.4.dist-info/top_level.txt
banglanltk-0.0.4.dist-info/RECORD
