Metadata-Version: 2.1
Name: banglanltk
Version: 0.0.4
Summary: Bangla Natural Language Processing Toolkit
Home-page: UNKNOWN
Author: Piyal Roy
Author-email: piyalroy00@gmail.com
License: UNKNOWN
Keywords: NLP,bangla,tagging,tokenizing,stemming,cleaning,synonym,natural language processing
Platform: UNKNOWN
Classifier: Programming Language :: Python :: 3
Classifier: Programming Language :: Python :: 3.5
Classifier: Programming Language :: Python :: 3.6
Classifier: Programming Language :: Python :: 3.7
Classifier: Programming Language :: Python :: 3.8
Classifier: License :: OSI Approved :: MIT License
Classifier: Operating System :: OS Independent
